{
  "protocol_version" : "0.0.6",
  "configuration" : {
    "version" : "(6.13.0) (explicit/a02757a97ef)",
    "tlc" : "__thread",
    "sigsgev" : "normal",
    "notifications" : "kqueue",
    "architecture" : "arm64",
    "disabled_features" : "com,shared_perfcounters",
    "smallconfig" : "disabled",
    "bigarrays" : "disabled",
    "softdebug" : "enabled",
    "interpreter" : "enabled",
    "llvm_support" : "disabled",
    "suspend" : "preemptive"
  },
  "memory" : {
    "Resident Size" : "1186742272",
    "Virtual Size" : "422428721152",
    "minor_gc_time" : "0",
    "major_gc_time" : "1648999",
    "minor_gc_count" : "0",
    "major_gc_count" : "116",
    "major_gc_time_concurrent" : "0"
 },
  "threads" : [
 {
    "is_managed" : false,
    "offset_free_hash" : "0x0",
    "offset_rich_hash" : "0x0",
    "crashed" : true,
    "native_thread_id" : "0x1e4721000",
    "thread_info_addr" : "0x1358f9800",
    "thread_name" : "tid_103",
    "ctx" : {
      "IP" : "0x10150ea84",
      "SP" : "0x16ee58fe0",
      "BP" : "0x16ee59000"
  },
    "unmanaged_frames" : [
  {
      "is_managed" : "false",
      "native_address" : "0x2ae985c58",
      "native_offset" : "0x00000"
   }
,
  {
      "is_managed" : "false",
      "native_address" : "0x2aeabc788",
      "native_offset" : "0x00000"
   }
,
  {
      "is_managed" : "false",
      "native_address" : "0x2aeabcae4",
      "native_offset" : "0x00000"
   }
,
  {
      "is_managed" : "false",
      "native_address" : "0x2aeabd0d4",
      "native_offset" : "0x00000"
   }
,
  {
      "is_managed" : "false",
      "native_address" : "0x2ae9c7a20",
      "native_offset" : "0x00000"
   }
,
  {
      "is_managed" : "false",
      "native_address" : "0x2ae989d5c",
      "native_offset" : "0x00000"
   }
,
  {
      "is_managed" : "false",
      "native_address" : "0x2ae91264c",
      "native_offset" : "0x00000"
   }
,
  {
      "is_managed" : "false",
      "native_address" : "0x18df71a24",
      "native_offset" : "0x00000"
   }
,
  {
      "is_managed" : "false",
      "native_address" : "0x10150ec2c",
      "native_offset" : "0x00000"
   }
,
  {
      "is_managed" : "false",
      "native_address" : "0x101503fd0",
      "native_offset" : "0x00000"
   }
,
  {
      "is_managed" : "false",
      "native_address" : "0x10840ba8c",
      "native_offset" : "0x00000"
   }
,
  {
      "is_managed" : "false",
      "native_address" : "0x10304299c",
      "native_offset" : "0x00000"
   }
,
  {
      "is_managed" : "false",
      "native_address" : "0x10304b7b4",
      "native_offset" : "0x00000"
   }
,
  {
      "is_managed" : "false",
      "native_address" : "0x10304a36c",
      "native_offset" : "0x00000"
   }
,
  {
      "is_managed" : "false",
      "native_address" : "0x10304999c",
      "native_offset" : "0x00000"
   }
,
  {
      "is_managed" : "false",
      "native_address" : "0x102fe5c74",
      "native_offset" : "0x00000"
   }
,
  {
      "is_managed" : "false",
      "native_address" : "0x103969a64",
      "native_offset" : "0x00000"
   }
,
  {
      "is_managed" : "false",
      "native_address" : "0x102e51200",
      "native_offset" : "0x00000"
   }
,
  {
      "is_managed" : "false",
      "native_address" : "0x102e504c0",
      "native_offset" : "0x00000"
   }
,
  {
      "is_managed" : "false",
      "native_address" : "0x103934294",
      "native_offset" : "0x00000"
   }
,
  {
      "is_managed" : "false",
      "native_address" : "0x102e794d4",
      "native_offset" : "0x00000"
   }
,
  {
      "is_managed" : "false",
      "native_address" : "0x102ebabb4",
      "native_offset" : "0x00000"
   }
,
  {
      "is_managed" : "false",
      "native_address" : "0x102ea86c4",
      "native_offset" : "0x00000"
   }
,
  {
      "is_managed" : "false",
      "native_address" : "0x102ecb4f4",
      "native_offset" : "0x00000"
   }
,
  {
      "is_managed" : "false",
      "native_address" : "0x102eaa73c",
      "native_offset" : "0x00000"
   }
,
  {
      "is_managed" : "false",
      "native_address" : "0x102eac200",
      "native_offset" : "0x00000"
   }
,
  {
      "is_managed" : "false",
      "native_address" : "0x102a78c50",
      "native_offset" : "0x00000"
   }
,
  {
      "is_managed" : "false",
      "native_address" : "0x103814910",
      "native_offset" : "0x00000"
   }
,
  {
      "is_managed" : "false",
      "native_address" : "0x18e014570",
      "native_offset" : "0x00000"
   }
,
  {
      "is_managed" : "false",
      "native_address" : "0x18e0a865c",
      "native_offset" : "0x00000"
   }
,
  {
      "is_managed" : "false",
      "native_address" : "0x18e0a85a4",
      "native_offset" : "0x00000"
   }
,
  {
      "is_managed" : "false",
      "native_address" : "0x18dfe31dc",
      "native_offset" : "0x00000"
   }
,
  {
      "is_managed" : "false",
      "native_address" : "0x18f0d5ff0",
      "native_offset" : "0x00000"
   }
,
  {
      "is_managed" : "false",
      "native_address" : "0x191802280",
      "native_offset" : "0x00000"
   }
,
  {
      "is_managed" : "false",
      "native_address" : "0x191802030",
      "native_offset" : "0x00000"
   }
,
  {
      "is_managed" : "false",
      "native_address" : "0x191800578",
      "native_offset" : "0x00000"
   }
,
  {
      "is_managed" : "false",
      "native_address" : "0x191800174",
      "native_offset" : "0x00000"
   }
,
  {
      "is_managed" : "false",
      "native_address" : "0x18f0fe414",
      "native_offset" : "0x00000"
   }
,
  {
      "is_managed" : "false",
      "native_address" : "0x18f0fe208",
      "native_offset" : "0x00000"
   }
,
  {
      "is_managed" : "false",
      "native_address" : "0x194f74dc0",
      "native_offset" : "0x00000"
   }
,
  {
      "is_managed" : "false",
      "native_address" : "0x194f746e8",
      "native_offset" : "0x00000"
   }
,
  {
      "is_managed" : "false",
      "native_address" : "0x194f6dcf8",
      "native_offset" : "0x00000"
   }
,
  {
      "is_managed" : "false",
      "native_address" : "0x1985dc2d4",
      "native_offset" : "0x00000"
   }
,
  {
      "is_managed" : "false",
      "native_address" : "0x1917fabb0",
      "native_offset" : "0x00000"
   }
,
  {
      "is_managed" : "false",
      "native_address" : "0x191fd4980",
      "native_offset" : "0x00000"
   }
,
  {
      "is_managed" : "false",
      "native_address" : "0x1917edd50",
      "native_offset" : "0x00000"
   }
,
  {
      "is_managed" : "false",
      "native_address" : "0x1917c5014",
      "native_offset" : "0x00000"
   }
,
  {
      "is_managed" : "false",
      "native_address" : "0x103812e14",
      "native_offset" : "0x00000"
   }
,
  {
      "is_managed" : "false",
      "native_address" : "0x10381314c",
      "native_offset" : "0x00000"
   }
,
  {
      "is_managed" : "false",
      "native_address" : "0x18dbc10e0",
      "native_offset" : "0x00000"
   }

  ]
 },
 {
    "is_managed" : true,
    "offset_free_hash" : "0x1224727402",
    "offset_rich_hash" : "0x12247275cb",
    "crashed" : false,
    "native_thread_id" : "0x2cea07000",
    "thread_info_addr" : "0x127836e00",
    "thread_name" : "Timer-Scheduler",
    "ctx" : {
      "IP" : "0x18df0506c",
      "SP" : "0x2cea05ed0",
      "BP" : "0x2cea05f60"
  },
    "managed_frames" : [
  {
      "is_managed" : "false",
      "native_address" : "unregistered"
   }
,
  {
      "is_managed" : "true",
      "guid" : "5E2D116F-98D1-40D0-A76E-C8A673A2A4AC",
      "token" : "0x00000",
      "native_offset" : "0x0",
      "filename" : "mscorlib.dll",
      "sizeofimage" : "0x470000",
      "timestamp" : "0x97783c76",
      "il_offset" : "0xffffffff"
   }
,
  {
      "is_managed" : "true",
      "guid" : "5E2D116F-98D1-40D0-A76E-C8A673A2A4AC",
      "token" : "0x60020b2",
      "native_offset" : "0x0",
      "filename" : "mscorlib.dll",
      "sizeofimage" : "0x470000",
      "timestamp" : "0x97783c76",
      "il_offset" : "0x00044"
   }
,
  {
      "is_managed" : "true",
      "guid" : "5E2D116F-98D1-40D0-A76E-C8A673A2A4AC",
      "token" : "0x600209e",
      "native_offset" : "0x0",
      "filename" : "mscorlib.dll",
      "sizeofimage" : "0x470000",
      "timestamp" : "0x97783c76",
      "il_offset" : "0x00014"
   }
,
  {
      "is_managed" : "true",
      "guid" : "5E2D116F-98D1-40D0-A76E-C8A673A2A4AC",
      "token" : "0x600209d",
      "native_offset" : "0x0",
      "filename" : "mscorlib.dll",
      "sizeofimage" : "0x470000",
      "timestamp" : "0x97783c76",
      "il_offset" : "0x00000"
   }
,
  {
      "is_managed" : "true",
      "guid" : "5E2D116F-98D1-40D0-A76E-C8A673A2A4AC",
      "token" : "0x6002098",
      "native_offset" : "0x0",
      "filename" : "mscorlib.dll",
      "sizeofimage" : "0x470000",
      "timestamp" : "0x97783c76",
      "il_offset" : "0x00019"
   }
,
  {
      "is_managed" : "true",
      "guid" : "5E2D116F-98D1-40D0-A76E-C8A673A2A4AC",
      "token" : "0x600209b",
      "native_offset" : "0x0",
      "filename" : "mscorlib.dll",
      "sizeofimage" : "0x470000",
      "timestamp" : "0x97783c76",
      "il_offset" : "0x00000"
   }
,
  {
      "is_managed" : "true",
      "guid" : "5E2D116F-98D1-40D0-A76E-C8A673A2A4AC",
      "token" : "0x600215a",
      "native_offset" : "0x0",
      "filename" : "mscorlib.dll",
      "sizeofimage" : "0x470000",
      "timestamp" : "0x97783c76",
      "il_offset" : "0x0003c"
   }
,
  {
      "is_managed" : "true",
      "guid" : "5E2D116F-98D1-40D0-A76E-C8A673A2A4AC",
      "token" : "0x6001f7d",
      "native_offset" : "0x0",
      "filename" : "mscorlib.dll",
      "sizeofimage" : "0x470000",
      "timestamp" : "0x97783c76",
      "il_offset" : "0x00014"
   }
,
  {
      "is_managed" : "true",
      "guid" : "5E2D116F-98D1-40D0-A76E-C8A673A2A4AC",
      "token" : "0x6001f25",
      "native_offset" : "0x0",
      "filename" : "mscorlib.dll",
      "sizeofimage" : "0x470000",
      "timestamp" : "0x97783c76",
      "il_offset" : "0x00071"
   }
,
  {
      "is_managed" : "true",
      "guid" : "5E2D116F-98D1-40D0-A76E-C8A673A2A4AC",
      "token" : "0x6001f23",
      "native_offset" : "0x0",
      "filename" : "mscorlib.dll",
      "sizeofimage" : "0x470000",
      "timestamp" : "0x97783c76",
      "il_offset" : "0x00000"
   }
,
  {
      "is_managed" : "true",
      "guid" : "5E2D116F-98D1-40D0-A76E-C8A673A2A4AC",
      "token" : "0x6001f22",
      "native_offset" : "0x0",
      "filename" : "mscorlib.dll",
      "sizeofimage" : "0x470000",
      "timestamp" : "0x97783c76",
      "il_offset" : "0x0002b"
   }
,
  {
      "is_managed" : "true",
      "guid" : "5E2D116F-98D1-40D0-A76E-C8A673A2A4AC",
      "token" : "0x6001f7f",
      "native_offset" : "0x0",
      "filename" : "mscorlib.dll",
      "sizeofimage" : "0x470000",
      "timestamp" : "0x97783c76",
      "il_offset" : "0x00008"
   }
,
  {
      "is_managed" : "true",
      "guid" : "5E2D116F-98D1-40D0-A76E-C8A673A2A4AC",
      "token" : "0x00000",
      "native_offset" : "0x0",
      "filename" : "mscorlib.dll",
      "sizeofimage" : "0x470000",
      "timestamp" : "0x97783c76",
      "il_offset" : "0x00065"
   }

  ],
  "unmanaged_frames" : [
 {
    "is_managed" : "false",
    "native_address" : "0x2ae985c58",
    "native_offset" : "0x00000"
  }
,
 {
    "is_managed" : "false",
    "native_address" : "0x2aeabc788",
    "native_offset" : "0x00000"
  }
,
 {
    "is_managed" : "false",
    "native_address" : "0x2aeabcae4",
    "native_offset" : "0x00000"
  }
,
 {
    "is_managed" : "false",
    "native_address" : "0x2aeabc8ac",
    "native_offset" : "0x00000"
  }
,
 {
    "is_managed" : "false",
    "native_address" : "0x2ae9c6bd4",
    "native_offset" : "0x00000"
  }
,
 {
    "is_managed" : "false",
    "native_address" : "0x18df71a24",
    "native_offset" : "0x00000"
  }
,
 {
    "is_managed" : "false",
    "native_address" : "0x18df425fc",
    "native_offset" : "0x00000"
  }
,
 {
    "is_managed" : "false",
    "native_address" : "0x2aeb0be30",
    "native_offset" : "0x00000"
  }
,
 {
    "is_managed" : "false",
    "native_address" : "0x2aeac84b0",
    "native_offset" : "0x00000"
  }
,
 {
    "is_managed" : "false",
    "native_address" : "0x2aeac82e4",
    "native_offset" : "0x00000"
  }
,
 {
    "is_managed" : "false",
    "native_address" : "0x2aeac857c",
    "native_offset" : "0x00000"
  }
,
 {
    "is_managed" : "false",
    "native_address" : "0x2aeab7b28",
    "native_offset" : "0x00000"
  }
,
 {
    "is_managed" : "false",
    "native_address" : "0x2aea62388",
    "native_offset" : "0x00000"
  }
,
 {
    "is_managed" : "true",
    "guid" : "5E2D116F-98D1-40D0-A76E-C8A673A2A4AC",
    "token" : "0x00000",
    "native_offset" : "0x0",
    "filename" : "mscorlib.dll",
    "sizeofimage" : "0x470000",
    "timestamp" : "0x97783c76",
    "il_offset" : "0x00000"
  }
,
 {
    "is_managed" : "true",
    "guid" : "5E2D116F-98D1-40D0-A76E-C8A673A2A4AC",
    "token" : "0x60020b2",
    "native_offset" : "0x0",
    "filename" : "mscorlib.dll",
    "sizeofimage" : "0x470000",
    "timestamp" : "0x97783c76",
    "il_offset" : "0x00000"
  }
,
 {
    "is_managed" : "true",
    "guid" : "5E2D116F-98D1-40D0-A76E-C8A673A2A4AC",
    "token" : "0x600209e",
    "native_offset" : "0x0",
    "filename" : "mscorlib.dll",
    "sizeofimage" : "0x470000",
    "timestamp" : "0x97783c76",
    "il_offset" : "0x00000"
  }
,
 {
    "is_managed" : "true",
    "guid" : "5E2D116F-98D1-40D0-A76E-C8A673A2A4AC",
    "token" : "0x600209d",
    "native_offset" : "0x0",
    "filename" : "mscorlib.dll",
    "sizeofimage" : "0x470000",
    "timestamp" : "0x97783c76",
    "il_offset" : "0x00000"
  }
,
 {
    "is_managed" : "true",
    "guid" : "5E2D116F-98D1-40D0-A76E-C8A673A2A4AC",
    "token" : "0x6002098",
    "native_offset" : "0x0",
    "filename" : "mscorlib.dll",
    "sizeofimage" : "0x470000",
    "timestamp" : "0x97783c76",
    "il_offset" : "0x00000"
  }
,
 {
    "is_managed" : "true",
    "guid" : "5E2D116F-98D1-40D0-A76E-C8A673A2A4AC",
    "token" : "0x600209b",
    "native_offset" : "0x0",
    "filename" : "mscorlib.dll",
    "sizeofimage" : "0x470000",
    "timestamp" : "0x97783c76",
    "il_offset" : "0x00000"
  }
,
 {
    "is_managed" : "true",
    "guid" : "5E2D116F-98D1-40D0-A76E-C8A673A2A4AC",
    "token" : "0x600215a",
    "native_offset" : "0x0",
    "filename" : "mscorlib.dll",
    "sizeofimage" : "0x470000",
    "timestamp" : "0x97783c76",
    "il_offset" : "0x00000"
  }
,
 {
    "is_managed" : "true",
    "guid" : "5E2D116F-98D1-40D0-A76E-C8A673A2A4AC",
    "token" : "0x6001f7d",
    "native_offset" : "0x0",
    "filename" : "mscorlib.dll",
    "sizeofimage" : "0x470000",
    "timestamp" : "0x97783c76",
    "il_offset" : "0x00000"
  }
,
 {
    "is_managed" : "true",
    "guid" : "5E2D116F-98D1-40D0-A76E-C8A673A2A4AC",
    "token" : "0x6001f25",
    "native_offset" : "0x0",
    "filename" : "mscorlib.dll",
    "sizeofimage" : "0x470000",
    "timestamp" : "0x97783c76",
    "il_offset" : "0x00000"
  }
,
 {
    "is_managed" : "true",
    "guid" : "5E2D116F-98D1-40D0-A76E-C8A673A2A4AC",
    "token" : "0x6001f23",
    "native_offset" : "0x0",
    "filename" : "mscorlib.dll",
    "sizeofimage" : "0x470000",
    "timestamp" : "0x97783c76",
    "il_offset" : "0x00000"
  }
,
 {
    "is_managed" : "true",
    "guid" : "5E2D116F-98D1-40D0-A76E-C8A673A2A4AC",
    "token" : "0x6001f22",
    "native_offset" : "0x0",
    "filename" : "mscorlib.dll",
    "sizeofimage" : "0x470000",
    "timestamp" : "0x97783c76",
    "il_offset" : "0x00000"
  }
,
 {
    "is_managed" : "true",
    "guid" : "5E2D116F-98D1-40D0-A76E-C8A673A2A4AC",
    "token" : "0x6001f7f",
    "native_offset" : "0x0",
    "filename" : "mscorlib.dll",
    "sizeofimage" : "0x470000",
    "timestamp" : "0x97783c76",
    "il_offset" : "0x00000"
  }
,
 {
    "is_managed" : "true",
    "guid" : "5E2D116F-98D1-40D0-A76E-C8A673A2A4AC",
    "token" : "0x00000",
    "native_offset" : "0x0",
    "filename" : "mscorlib.dll",
    "sizeofimage" : "0x470000",
    "timestamp" : "0x97783c76",
    "il_offset" : "0x00000"
  }
,
 {
    "is_managed" : "false",
    "native_address" : "0x2ae91590c",
    "native_offset" : "0x00000"
  }
,
 {
    "is_managed" : "false",
    "native_address" : "0x2aea9b6a8",
    "native_offset" : "0x00000"
  }
,
 {
    "is_managed" : "false",
    "native_address" : "0x2aea9d2a4",
    "native_offset" : "0x00000"
  }
,
 {
    "is_managed" : "false",
    "native_address" : "0x2aeabd5e8",
    "native_offset" : "0x00000"
  }
,
 {
    "is_managed" : "false",
    "native_address" : "0x2aeabd3a0",
    "native_offset" : "0x00000"
  }
,
 {
    "is_managed" : "false",
    "native_address" : "0x2aeb3ccb0",
    "native_offset" : "0x00000"
  }
,
 {
    "is_managed" : "false",
    "native_address" : "0x2aeb3cc38",
    "native_offset" : "0x00000"
  }
,
 {
    "is_managed" : "false",
    "native_address" : "0x18df42034",
    "native_offset" : "0x00000"
  }
,
 {
    "is_managed" : "false",
    "native_address" : "0x18df3ce3c",
    "native_offset" : "0x00000"
  }

 ]
},
{
  "is_managed" : false,
  "offset_free_hash" : "0x0",
  "offset_rich_hash" : "0x0",
  "crashed" : false,
  "native_thread_id" : "0x2ae6e7000",
  "thread_info_addr" : "0x134946000",
  "thread_name" : "Finalizer",
  "ctx" : {
    "IP" : "0x18df017f0",
    "SP" : "0x2ae6e6dd0",
    "BP" : "0x2ae6e6e50"
 },
  "unmanaged_frames" : [
 {
    "is_managed" : "false",
    "native_address" : "0x2ae985c58",
    "native_offset" : "0x00000"
  }
,
 {
    "is_managed" : "false",
    "native_address" : "0x2aeabc788",
    "native_offset" : "0x00000"
  }
,
 {
    "is_managed" : "false",
    "native_address" : "0x2aeabcae4",
    "native_offset" : "0x00000"
  }
,
 {
    "is_managed" : "false",
    "native_address" : "0x2aeabc8ac",
    "native_offset" : "0x00000"
  }
,
 {
    "is_managed" : "false",
    "native_address" : "0x2ae9c6bd4",
    "native_offset" : "0x00000"
  }
,
 {
    "is_managed" : "false",
    "native_address" : "0x18df71a24",
    "native_offset" : "0x00000"
  }
,
 {
    "is_managed" : "false",
    "native_address" : "0x2aeaf6294",
    "native_offset" : "0x00000"
  }
,
 {
    "is_managed" : "false",
    "native_address" : "0x2aeabd4f4",
    "native_offset" : "0x00000"
  }
,
 {
    "is_managed" : "false",
    "native_address" : "0x2aeabd3a0",
    "native_offset" : "0x00000"
  }
,
 {
    "is_managed" : "false",
    "native_address" : "0x2aeb3ccb0",
    "native_offset" : "0x00000"
  }
,
 {
    "is_managed" : "false",
    "native_address" : "0x2aeb3cc38",
    "native_offset" : "0x00000"
  }
,
 {
    "is_managed" : "false",
    "native_address" : "0x18df42034",
    "native_offset" : "0x00000"
  }
,
 {
    "is_managed" : "false",
    "native_address" : "0x18df3ce3c",
    "native_offset" : "0x00000"
  }

 ]
},
{
  "is_managed" : false,
  "offset_free_hash" : "0x0",
  "offset_rich_hash" : "0x0",
  "crashed" : false,
  "native_thread_id" : "0x2ae8f3000",
  "thread_info_addr" : "0x134949200",
  "thread_name" : "Debugger agent",
  "ctx" : {
    "IP" : "0x18df0a1c0",
    "SP" : "0x2ae8f2aa0",
    "BP" : "0x2ae8f2ae0"
 },
  "unmanaged_frames" : [
 {
    "is_managed" : "false",
    "native_address" : "0x2ae985c58",
    "native_offset" : "0x00000"
  }
,
 {
    "is_managed" : "false",
    "native_address" : "0x2aeabc788",
    "native_offset" : "0x00000"
  }
,
 {
    "is_managed" : "false",
    "native_address" : "0x2aeabcae4",
    "native_offset" : "0x00000"
  }
,
 {
    "is_managed" : "false",
    "native_address" : "0x2aeabc8ac",
    "native_offset" : "0x00000"
  }
,
 {
    "is_managed" : "false",
    "native_address" : "0x2ae9c6bd4",
    "native_offset" : "0x00000"
  }
,
 {
    "is_managed" : "false",
    "native_address" : "0x18df71a24",
    "native_offset" : "0x00000"
  }
,
 {
    "is_managed" : "false",
    "native_address" : "0x2ae9fc3e0",
    "native_offset" : "0x00000"
  }
,
 {
    "is_managed" : "false",
    "native_address" : "0x2ae9f3760",
    "native_offset" : "0x00000"
  }
,
 {
    "is_managed" : "false",
    "native_address" : "0x2aeabd4f4",
    "native_offset" : "0x00000"
  }
,
 {
    "is_managed" : "false",
    "native_address" : "0x2aeabd3a0",
    "native_offset" : "0x00000"
  }
,
 {
    "is_managed" : "false",
    "native_address" : "0x2aeb3ccb0",
    "native_offset" : "0x00000"
  }
,
 {
    "is_managed" : "false",
    "native_address" : "0x2aeb3cc38",
    "native_offset" : "0x00000"
  }
,
 {
    "is_managed" : "false",
    "native_address" : "0x18df42034",
    "native_offset" : "0x00000"
  }
,
 {
    "is_managed" : "false",
    "native_address" : "0x18df3ce3c",
    "native_offset" : "0x00000"
  }

 ]
}
]
}